oapapersloader/__init__.py
oapapersloader/bib_entry.py
oapapersloader/datasets.py
oapapersloader/document.py
oapapersloader/document_datasets.py
oapapersloader/hierarchy.py
oapapersloader/myjson.py
oapapersloader-1.0.1.dist-info/METADATA
oapapersloader-1.0.1.dist-info/WHEEL
oapapersloader-1.0.1.dist-info/top_level.txt
oapapersloader-1.0.1.dist-info/RECORD
