Metadata-Version: 2.1
Name: oapapersloader
Version: 1.0.1
Summary: Package for working with OAPapers dataset.
Home-page: https://github.com/KNOT-FIT-BUT/OAPapersLoader
Author: Martin Dočekal
License: The Unlicense
Keywords: dataset,OAPapers loader,OAPapers dataset
Requires-Python: >=3.9
Requires-Dist: windpyutils ~=2.0.48
Requires-Dist: tqdm
Requires-Dist: orjson ~=3.9.5
